[
  {
    "id": "1760C",
    "name": "Advantage",
    "rating": 900,
    "url": "https://codeforces.com/contest/1760/problem/C"
  },
  {
    "id": "1742E",
    "name": "Scuza",
    "rating": 1100,
    "url": "https://codeforces.com/contest/1742/problem/E"
  },
  {
    "id": "1722C",
    "name": "Word Game",
    "rating": 800,
    "url": "https://codeforces.com/contest/1722/problem/C"
  },
  {
    "id": "1676H2",
    "name": "Maximum Crossings (Hard Version)",
    "rating": 1400,
    "url": "https://codeforces.com/contest/1676/problem/H2"
  }
]
